<?xml version="1.0" encoding="UTF-8"?>
<results title="childobese">
 <result pre=": Single-Method Research Article The Sociocultural Factors Underlying Latina Mothers’" exact="Infant" post="Feeding Practices https://orcid.org/0000-0002-4032-6692 Cheney Ann M. 1 Nieri Tanya"/>
 <result pre="to curb early childhood obesity risk, including the Early Childhood" exact="Obesity" post="Prevention Program, and the Infant Feeding and Activity and"/>
 <result pre="risk, including the Early Childhood Obesity Prevention Program, and the" exact="Infant" post="Feeding and Activity and Nutrition Trail (Infant Extend). However,"/>
 <result pre="not consider culture, family dynamics, or the meaning of foods." exact="Infant" post="feeding is a complex practice shaped by multiple factors"/>
 <result pre="A. ( 2006). Early infant feeding decisions in low-income Latinas." exact="Breastfeeding" post="Medicine, 1, 225– 235. doi: 10.1089/bfm.2006.1.225 17661603 Calzada E."/>
 <result pre="( 2016). Counseling immigrant parents about food and feeding practices:" exact="Public health" post="nurses’ experiences . Public Health Nursing, 33, 343– 350."/>
 <result pre="perceptions of infant complementary feeding: A qualitative evidence synthesis ." exact="Obesity" post="Reviews, 19, 501– 517. doi: 10.1111/obr.12653 29243375 Minkler M."/>
 <result pre="10.1542/peds.2013-1326 24639273 Pulgaron E. R. Delamater A. M. ( 2014)." exact="Obesity" post="and type 2 diabetes in children: Epidemiology and treatment."/>
 <result pre="and type 2 diabetes in children: Epidemiology and treatment. Current" exact="Diabetes" post="Reports, 14, 508. doi: 10.1007/s11892-014-0508y 24919749 Ryan G. Bernard"/>
</results>
