<?xml version="1.0" encoding="UTF-8"?>
<snippetsTree>
 <snippets file="obesemini/PMC6324517/results/search/country/results.xml">
  <result pre="Res Protoc ResProt JMIR Research Protocols 1929-0748 JMIR Publications Toronto," exact="Canada" post="pmcid: 6324517 v7i12e11329 pmid: 30578226 doi: 10.2196/11329 : Protocol:"/>
  <result pre="Health Sciences E-Wing, 104 Clinic Place Saskatoon, SK, S7N 2Z4" exact="Canada" post="1 306 966 6341 1 306 966 6377 vatan.h@usask.ca"/>
  <result pre="Iran [2], College of Medicine University of Saskatchewan Saskatoon, SK" exact="Canada" post="[3], College of Kinesiology University of Saskatchewan Saskatoon, SK"/>
  <result pre="Canada [3], College of Kinesiology University of Saskatchewan Saskatoon, SK" exact="Canada" post="[4], Department of Family Medicine Université de Sherbrooke Moncton,"/>
  <result pre="[4], Department of Family Medicine Université de Sherbrooke Moncton, NB" exact="Canada" post="[5], College of Pharmacy and Nutrition University of Saskatchewan"/>
  <result pre="College of Pharmacy and Nutrition University of Saskatchewan Saskatoon, SK" exact="Canada" post="Corresponding Author: Hassan Vatanparast vatan.h@usask.ca collection: 2018-12 epub: 2018-12-12"/>
  <result pre="has been developed and initiated in the Saskatchewan province of" exact="Canada" post="and is expected to expand to the whole country"/>
  <result pre="initiative, which is now successfully running in 2 provinces in" exact="Canada" post="[ 26]. &quot;Iran Healthy Start (IHS)/Aghazi Salem, Koodake Irani&quot;"/>
  <result pre="[ 33, 34] has been first designed and validated in" exact="Canada" post="in different languages for assessing eating habits and nutrition"/>
  <result pre="2006 76-85 1992 10.1111/j.1651-2227.2006.tb02378.x 3 World Health Organization 2015 Geneva," exact="Switzerland" post="World Health Organization Draft Final Report of the Commission"/>
  <result pre="of Overweight and Obesity in Adults, Adolescents and Children in" exact="Australia" post="http://www.webcitation.org/71Mq5DNEF 12 Jones RA Okely AD Physical activity recommendations"/>
  <result pre="T Hinkley T Ridgers N Canberra, Australia: Common wealth of" exact="Australia" post="2012 A systematic review to update the Australian physical"/>
  <result pre="physical activity questionnaire developed for parents of preschool children in" exact="Mexico" post="J Health Popul Nutr 2012 12 30 4 439"/>
 </snippets>
</snippetsTree>
